ai71/README.md
ai71/__init__.py
ai71/clients/base_client.py
ai71/clients/client.py
ai71/clients/error_handler.py
ai71/exceptions.py
ai71/py.typed
ai71/resources/base_resource.py
ai71/resources/chat.py
ai71/resources/chat_completions.py
ai71/resources/completions.py
ai71/resources/models.py
ai71/types/chat_completion.py
ai71/types/chat_completion_chunk.py
ai71/types/chat_completion_message.py
ai71/types/completion.py
ai71/types/completion_chunk.py
ai71/types/completion_usage.py
ai71/types/finish_reason.py
ai71/types/models.py
ai71-1.0.1.dist-info/METADATA
ai71-1.0.1.dist-info/WHEEL
ai71-1.0.1.dist-info/RECORD
