Metadata-Version: 2.3
Name: ai71
Version: 1.0.1
Summary: The official Python library for the AI71 API
Author: AI71 Platform
Author-email: platform@ai71.ai
Requires-Python: >=3.8,<4.0
Classifier: Programming Language :: Python :: 3
Classifier: Programming Language :: Python :: 3.8
Classifier: Programming Language :: Python :: 3.9
Classifier: Programming Language :: Python :: 3.10
Classifier: Programming Language :: Python :: 3.11
Classifier: Programming Language :: Python :: 3.12
Classifier: Programming Language :: Python :: 3.13
Requires-Dist: httpx (>=0.25.2,<0.26.0)
Requires-Dist: httpx-sse (>=0.3.1,<0.4.0)
Requires-Dist: pydantic (>=2.5.2,<3.0.0)
